chainbase/hybrid_rerank_retrieval/__init__.py
chainbase/hybrid_rerank_retrieval/ai_services.py
chainbase/hybrid_rerank_retrieval/document.py
chainbase/hybrid_rerank_retrieval/document_crud.py
chainbase/hybrid_rerank_retrieval/marco_rerank_retriever.py
chainbase/hybrid_rerank_retrieval/openai_retrieve_summarize_service.py
chainbase/hybrid_rerank_retrieval/retrieval_service.py
chainbase/hybrid_rerank_retrieval/router.py
chainbase/hybrid_rerank_retrieval/stis_embeddings.py
chainbase/hybrid_rerank_retrieval/template.html
chainbase_hrr-0.0.3.dist-info/METADATA
chainbase_hrr-0.0.3.dist-info/WHEEL
chainbase_hrr-0.0.3.dist-info/RECORD
